MANIFEST.in
README.rst
setup.py
aliyun_python_sdk_cloudphoto.egg-info/PKG-INFO
aliyun_python_sdk_cloudphoto.egg-info/SOURCES.txt
aliyun_python_sdk_cloudphoto.egg-info/dependency_links.txt
aliyun_python_sdk_cloudphoto.egg-info/requires.txt
aliyun_python_sdk_cloudphoto.egg-info/top_level.txt
aliyunsdkcloudphoto/__init__.py
aliyunsdkcloudphoto/request/__init__.py
aliyunsdkcloudphoto/request/v20170711/ActivatePhotosRequest.py
aliyunsdkcloudphoto/request/v20170711/AddAlbumPhotosRequest.py
aliyunsdkcloudphoto/request/v20170711/CreateAlbumRequest.py
aliyunsdkcloudphoto/request/v20170711/CreateEventRequest.py
aliyunsdkcloudphoto/request/v20170711/CreatePhotoRequest.py
aliyunsdkcloudphoto/request/v20170711/CreatePhotoStoreRequest.py
aliyunsdkcloudphoto/request/v20170711/CreateTransactionRequest.py
aliyunsdkcloudphoto/request/v20170711/DeleteAlbumsRequest.py
aliyunsdkcloudphoto/request/v20170711/DeleteEventRequest.py
aliyunsdkcloudphoto/request/v20170711/DeleteFacesRequest.py
aliyunsdkcloudphoto/request/v20170711/DeletePhotoStoreRequest.py
aliyunsdkcloudphoto/request/v20170711/DeletePhotosRequest.py
aliyunsdkcloudphoto/request/v20170711/EditEventRequest.py
aliyunsdkcloudphoto/request/v20170711/EditPhotoStoreRequest.py
aliyunsdkcloudphoto/request/v20170711/EditPhotosRequest.py
aliyunsdkcloudphoto/request/v20170711/FetchAlbumTagPhotosRequest.py
aliyunsdkcloudphoto/request/v20170711/FetchLibrariesRequest.py
aliyunsdkcloudphoto/request/v20170711/FetchMomentPhotosRequest.py
aliyunsdkcloudphoto/request/v20170711/FetchPhotosRequest.py
aliyunsdkcloudphoto/request/v20170711/GetAlbumsByNamesRequest.py
aliyunsdkcloudphoto/request/v20170711/GetDownloadUrlRequest.py
aliyunsdkcloudphoto/request/v20170711/GetDownloadUrlsRequest.py
aliyunsdkcloudphoto/request/v20170711/GetEventRequest.py
aliyunsdkcloudphoto/request/v20170711/GetFramedPhotoUrlsRequest.py
aliyunsdkcloudphoto/request/v20170711/GetLibraryRequest.py
aliyunsdkcloudphoto/request/v20170711/GetPhotoStoreRequest.py
aliyunsdkcloudphoto/request/v20170711/GetPhotosByMd5sRequest.py
aliyunsdkcloudphoto/request/v20170711/GetPhotosRequest.py
aliyunsdkcloudphoto/request/v20170711/GetPrivateAccessUrlsRequest.py
aliyunsdkcloudphoto/request/v20170711/GetPublicAccessUrlsRequest.py
